generatecv/__init__.py
generatecv/cv_generator.py
generatecv/models.py
generatecv/pdf_generator.py
generatecv/parser/yaml.py
generatecv/styles/__init__.py
generatecv/styles/base_style.py
generatecv/styles/classic_style.py
tool/example.yaml
tool/main.py
generatecv-0.0.15.dist-info/METADATA
generatecv-0.0.15.dist-info/WHEEL
generatecv-0.0.15.dist-info/entry_points.txt
generatecv-0.0.15.dist-info/RECORD
