Metadata-Version: 2.4
Name: generatecv
Version: 0.0.15
Summary: generatecv is a Python package for generating professional CVs (resumes) from structured data.
Project-URL: Homepage, https://github.com/yantology/generatecv
Project-URL: Repository, https://github.com/yantology/generatecv
Project-URL: Documentation, https://yantology.github.io/generatecv
Project-URL: Bug Reports, https://github.com/yantology/generatecv/issues
Project-URL: Source Code, https://github.com/yantology/generatecv
Project-URL: Changelog, https://github.com/yantology/generatecv/releases
Author-email: yantology <work@yantology.dev>
Maintainer-email: yantology <work@yantology.dev>
License: MIT
Keywords: cv,document,generator,pdf,professional,resume,template
Classifier: Development Status :: 3 - Alpha
Classifier: Intended Audience :: Developers
Classifier: Intended Audience :: End Users/Desktop
Classifier: License :: OSI Approved :: MIT License
Classifier: Operating System :: OS Independent
Classifier: Programming Language :: Python :: 3
Classifier: Programming Language :: Python :: 3 :: Only
Classifier: Programming Language :: Python :: 3.13
Classifier: Topic :: Office/Business
Classifier: Topic :: Text Processing :: Markup
Classifier: Topic :: Utilities
Classifier: Typing :: Typed
Requires-Python: >=3.13
Requires-Dist: email-validator>=2.0.0
Requires-Dist: pydantic>=2.11.5
Requires-Dist: pyyaml>=6.0.2
Requires-Dist: reportlab>=4.4.1
